smpl_debug/__init__.py
smpl_debug-1.3.0.dist-info/LICENSE
smpl_debug-1.3.0.dist-info/METADATA
smpl_debug-1.3.0.dist-info/WHEEL
smpl_debug-1.3.0.dist-info/RECORD
