Metadata-Version: 2.3
Name: smpl_debug
Version: 1.3.0
Summary: SiMPLe plotting and fitting
Author: Alexander Puck Neuwirth
Author-email: alexander@neuwirth-informatik.de
Requires-Python: >=3.8,<4.0
Classifier: Programming Language :: Python :: 3
Classifier: Programming Language :: Python :: 3.8
Classifier: Programming Language :: Python :: 3.9
Classifier: Programming Language :: Python :: 3.10
Classifier: Programming Language :: Python :: 3.11
Classifier: Programming Language :: Python :: 3.12
Classifier: Programming Language :: Python :: 3.13
Requires-Dist: smpl (>=1.5.0)
Project-URL: Repository, https://github.com/APN-Pucky/smpl_debug
